integration/__init__.py
integration/main.py
mylibrary/__init__.py
mylibrary/client.py
mylibrary/models.py
mylibrary/module1.py
tests/__init__.py
tests/test_module1.py
markslibrary-0.1.2.dist-info/LICENSE
markslibrary-0.1.2.dist-info/METADATA
markslibrary-0.1.2.dist-info/WHEEL
markslibrary-0.1.2.dist-info/top_level.txt
markslibrary-0.1.2.dist-info/RECORD
