Metadata-Version: 2.1
Name: markslibrary
Version: 0.1.2
Summary: A sample PyPI package
Home-page: https://github.com/ryvdx/hello-pypi
Author: Mark Sawczuk
Author-email: mark.sawczuk@ryveal.io
License: UNKNOWN
Platform: UNKNOWN
Classifier: License :: OSI Approved :: MIT License
Classifier: Programming Language :: Python :: 3
Classifier: Programming Language :: Python :: 3.6
Classifier: Programming Language :: Python :: 3.7
Classifier: Programming Language :: Python :: 3.8
Classifier: Programming Language :: Python :: 3.9
License-File: LICENSE
